{
  "$schema": "https://raw.githubusercontent.com/spdx/spdx-spec/v2.2.1/schemas/spdx-schema.json",
  "spdxVersion": "SPDX-2.2",
  "dataLicense": "CC0-1.0",
  "SPDXID": "SPDXRef-DOCUMENT",
  "documentNamespace": "https://spdx.org/spdxdocs/boost-tti-x64-linux-1.83.0-7fcd5e6b-0841-4d3e-94ee-c3383114d38a",
  "name": "boost-tti:x64-linux@1.83.0 c22ff702d6a94a4ba1c655506263d92a3eb28e4cf45e9fc706a89605e73b6a9d",
  "creationInfo": {
    "creators": [
      "Tool: vcpkg-4c1df40a3c5c5e18de299a99e9accb03c2a82e1e"
    ],
    "created": "2024-10-25T10:03:47Z"
  },
  "relationships": [
    {
      "spdxElementId": "SPDXRef-port",
      "relationshipType": "GENERATES",
      "relatedSpdxElement": "SPDXRef-binary"
    },
    {
      "spdxElementId": "SPDXRef-port",
      "relationshipType": "CONTAINS",
      "relatedSpdxElement": "SPDXRef-file-0"
    },
    {
      "spdxElementId": "SPDXRef-port",
      "relationshipType": "CONTAINS",
      "relatedSpdxElement": "SPDXRef-file-1"
    },
    {
      "spdxElementId": "SPDXRef-binary",
      "relationshipType": "GENERATED_FROM",
      "relatedSpdxElement": "SPDXRef-port"
    },
    {
      "spdxElementId": "SPDXRef-file-0",
      "relationshipType": "CONTAINED_BY",
      "relatedSpdxElement": "SPDXRef-port"
    },
    {
      "spdxElementId": "SPDXRef-file-1",
      "relationshipType": "CONTAINED_BY",
      "relatedSpdxElement": "SPDXRef-port"
    }
  ],
  "packages": [
    {
      "name": "boost-tti",
      "SPDXID": "SPDXRef-port",
      "versionInfo": "1.83.0",
      "downloadLocation": "git+https://github.com/microsoft/vcpkg@06c466d2662d638138c5318e4ad3a165974de862",
      "homepage": "https://github.com/boostorg/tti",
      "licenseConcluded": "BSL-1.0",
      "licenseDeclared": "NOASSERTION",
      "copyrightText": "NOASSERTION",
      "description": "Boost tti module",
      "comment": "This is the port (recipe) consumed by vcpkg."
    },
    {
      "name": "boost-tti:x64-linux",
      "SPDXID": "SPDXRef-binary",
      "versionInfo": "c22ff702d6a94a4ba1c655506263d92a3eb28e4cf45e9fc706a89605e73b6a9d",
      "downloadLocation": "NONE",
      "licenseConcluded": "BSL-1.0",
      "licenseDeclared": "NOASSERTION",
      "copyrightText": "NOASSERTION",
      "comment": "This is a binary package built by vcpkg."
    },
    {
      "SPDXID": "SPDXRef-resource-1",
      "name": "boostorg/tti",
      "downloadLocation": "git+https://github.com/boostorg/tti@boost-1.83.0",
      "licenseConcluded": "NOASSERTION",
      "licenseDeclared": "NOASSERTION",
      "copyrightText": "NOASSERTION",
      "checksums": [
        {
          "algorithm": "SHA512",
          "checksumValue": "5a134b60981d84858fe55b18c72737ce3c6a6d644972f86db5a465cc28257249c7288e333d14c2c6e8eca21fb3f6c17d74e41dbad6d4806616f230d2bc0c68ae"
        }
      ]
    }
  ],
  "files": [
    {
      "fileName": ".//root/.cache/vcpkg/registries/git-trees/06c466d2662d638138c5318e4ad3a165974de862/portfile.cmake",
      "SPDXID": "SPDXRef-file-0",
      "checksums": [
        {
          "algorithm": "SHA256",
          "checksumValue": "d8cf4472a354660b232589b45fe369a8240c2e66fc069ec61dbc3a4190061056"
        }
      ],
      "licenseConcluded": "NOASSERTION",
      "copyrightText": "NOASSERTION"
    },
    {
      "fileName": ".//root/.cache/vcpkg/registries/git-trees/06c466d2662d638138c5318e4ad3a165974de862/vcpkg.json",
      "SPDXID": "SPDXRef-file-1",
      "checksums": [
        {
          "algorithm": "SHA256",
          "checksumValue": "ca4dc67262a856e8dda0940c1f374e76605b12b651e0c32f75b892d3f246a60c"
        }
      ],
      "licenseConcluded": "NOASSERTION",
      "copyrightText": "NOASSERTION"
    }
  ]
}
